pyvistaqt/__init__.py
pyvistaqt/_version.py
pyvistaqt/counter.py
pyvistaqt/dialog.py
pyvistaqt/editor.py
pyvistaqt/plotting.py
pyvistaqt/rwi.py
pyvistaqt/utils.py
pyvistaqt/window.py
pyvistaqt/data/pyvista_logo_square.png
pyvistaqt-0.11.1.dist-info/AUTHORS.rst
pyvistaqt-0.11.1.dist-info/LICENSE
pyvistaqt-0.11.1.dist-info/METADATA
pyvistaqt-0.11.1.dist-info/WHEEL
pyvistaqt-0.11.1.dist-info/top_level.txt
pyvistaqt-0.11.1.dist-info/RECORD
