Metadata-Version: 2.1
Name: pyvistaqt
Version: 0.11.1
Summary: pyvista qt plotter
Home-page: https://github.com/pyvista/pyvistaqt
Author: PyVista Developers
Author-email: info@pyvista.org
License: MIT
Keywords: vtk numpy plotting mesh qt
Classifier: Development Status :: 4 - Beta
Classifier: Intended Audience :: Science/Research
Classifier: Topic :: Scientific/Engineering :: Information Analysis
Classifier: License :: OSI Approved :: MIT License
Classifier: Operating System :: Microsoft :: Windows
Classifier: Operating System :: POSIX
Classifier: Operating System :: MacOS
Classifier: Programming Language :: Python :: 3.7
Classifier: Programming Language :: Python :: 3.8
Classifier: Programming Language :: Python :: 3.9
Requires-Python: >=3.7
License-File: LICENSE
License-File: AUTHORS.rst
Requires-Dist: pyvista>=0.32.0
Requires-Dist: QtPy>=1.9.0
